Workbook

Sheet Breakdown
A1: 9145 Ellis Road | D1: Call ID: | E1: C1421763
A2: Melbourne, FL 32904 | D2: Currency: | E2: USD
A3: www.ussiglobal.com | D3: Invoice Date: | E3: 46205
D4: Completed Date: | E4: 46203
D5: Customer: | E5: Promethean
D6: Terms: | E6: Net Amt Due in 45
A8: =CONCATENATE("PROFORMA INVOICE: ",TEXT(E4,"MMMM YYYY")) -> PROFORMA INVOICE: June 2026
A10: Workshop | B10: Units of Measure | C10: Unit Price | D10: Quantity | E10: Total Amount
A11: Standard ‘Basic’ Panel Triage & Repair Small (65”-75”) | B11: Each | C11: 110 | D11: =COUNTIFS('Depot Repair'!C:C,"BASIC",'Depot Repair'!D:D,"Small") -> 87 | E11: =D11*C11 -> 9570
A12: Standard ‘Basic’ Panel Triage & Repair Large (86”) | B12: Each | C12: 135 | D12: =COUNTIFS('Depot Repair'!C:C,"BASIC",'Depot Repair'!D:D,"LARGE") -> 14 | E12: =D12*C12 -> 1890
A13: Advanced ‘Heavy’ Panel Triage & Repairs Small (65”-75”) | B13: Each | C13: 220 | D13: =COUNTIFS('Depot Repair'!C:C,"Heavy",'Depot Repair'!D:D,"Small") -> 36 | E13: =D13*C13 -> 7920
A14: Advanced ‘Heavy’ Panel Triage & Repairs Large (86”) | B14: Each | C14: 268 | D14: =COUNTIFS('Depot Repair'!C:C,"Heavy",'Depot Repair'!D:D,"Large") -> 24 | E14: =D14*C14 -> 6432
A16: Standard ‘Basic’ Panel Triage Small (65”-75”) | B16: Each | C16: 86 | D16: =COUNTIFS('Triage Units'!D:D,"BasicSmall-Triage") -> 2 | E16: =D16*C16 -> 172
A17: Standard ‘Basic’ Panel Triage Large (86”) | B17: Each | C17: 101 | D17: =COUNTIFS('Triage Units'!D:D,"BasicLarge-Triage") -> 2 | E17: =D17*C17 -> 202
A18: Advanced ‘Heavy’ Panel Triage Small (65”-75”) | B18: Each | C18: 152 | D18: =COUNTIFS('Triage Units'!D:D,"HeavySmall-Triage") -> 114 | E18: =D18*C18 -> 17328
A19: Advanced ‘Heavy’ Panel Triage Large (86”) | B19: Each | C19: 181 | D19: =COUNTIFS('Triage Units'!D:D,"HeavyLarge-Triage") -> 12 | E19: =D19*C19 -> 2172
A21: Standard ‘Basic’ Panel Repair Small (65”-75”) | B21: Each | C21: 64 | D21: =COUNTIFS('Depot Repair'!C:C,"BasicSmall - Previously Triaged") -> 1 | E21: =D21*C21 -> 64
A22: Standard ‘Basic’ Panel Repair Large (86”) | B22: Each | C22: 74 | D22: =COUNTIFS('Depot Repair'!C:C,"BasicLarge - Previously Triaged") -> 1 | E22: =D22*C22 -> 74
A23: Advanced ‘Heavy’ Panel Repair Small (65”-75”) | B23: Each | C23: 108 | D23: =COUNTIFS('Depot Repair'!C:C,"HeavySmall - Previously Triaged") -> 17 | E23: =D23*C23 -> 1836
A24: Advanced ‘Heavy’ Panel Repair Large (86”) | B24: Each | C24: 127 | D24: =COUNTIFS('Depot Repair'!C:C,"HeavyLarge - Previously Triaged") -> 10 | E24: =D24*C24 -> 1270
A26: Reboxing Fee | B26: Each | C26: 50 | D26: 0 | E26: =D26*C26 -> 0
A28: Immediate Scrap | B28: Each | C28: 19 | D28: =COUNTIFS('Depot Repair'!C:C,"Immediate Scrap") -> 0 | E28: =D28*C28 -> 0
A29: Salvage of Hardware and Scrap | B29: Each | C29: 28 | D29: =COUNTIFS('Depot Repair'!C:C,"Salvage of Hardware and Scrap") -> 64 | E29: =D29*C29 -> 1792
A31: Special Warehouse Projects | B31: Hourly | C31: 75 | D31: 0 | E31: =D31*C31 -> 0
A33: Parts Testing & Configuration | B33: Units of Measure | C33: Unit Price | D33: Quantity | E33: Total Amount
A34: PSU - Testing | B34: Each | C34: 7 | D34: =SUMIFS(TblPartTesting[Quantity],TblPartTesting[Type],"PSU") -> 30 | E34: =D34*C34 -> 210
A35: Mainboard Configure for Dispatch - Testing | B35: Each | C35: 52 | D35: =SUMIFS(TblPartTesting[Quantity],TblPartTesting[Type],"Mainboard Configure for Dispatch") -> 44 | E35: =D35*C35 -> 2288
A36: Mainboard - Testing | B36: Each | C36: 37 | D36: =SUMIFS(TblPartTesting[Quantity],TblPartTesting[Type],"Mainboard") -> 0 | E36: =D36*C36 -> 0
A37: AC-PCA - Testing | B37: Each | C37: 4 | D37: =SUMIFS(TblPartTesting[Quantity],TblPartTesting[Type],"AC-PCA") -> 8 | E37: =D37*C37 -> 32
A38: Keypad - Testing | B38: Each | C38: 4 | D38: =SUMIFS(TblPartTesting[Quantity],TblPartTesting[Type],"Keypad") -> 29 | E38: =D38*C38 -> 116
A39: Maintouch - Testing | B39: Each | C39: 37 | D39: =SUMIFS(TblPartTesting[Quantity],TblPartTesting[Type],"Maintouch") -> 13 | E39: =D39*C39 -> 481
A40: Ext-Input - Testing | B40: Each | C40: 7 | D40: =SUMIFS(TblPartTesting[Quantity],TblPartTesting[Type],"Ext-Input") -> 6 | E40: =D40*C40 -> 42
A41: OPS-PCA - Testing | B41: Each | C41: 4 | D41: =SUMIFS(TblPartTesting[Quantity],TblPartTesting[Type],"OPS-PCA") -> 3 | E41: =D41*C41 -> 12
A42: USB - Testing | B42: Each | C42: 4 | D42: =SUMIFS(TblPartTesting[Quantity],TblPartTesting[Type],"USB") -> 52 | E42: =D42*C42 -> 208
A43: Speaker Testing | B43: Each | C43: 4 | D43: =SUMIFS(TblPartTesting[Quantity],TblPartTesting[Type],"Speaker") -> 2 | E43: =D43*C43 -> 8
D45: Subtotal | E45: =SUM(E11:E43) -> 54119
D46: Tax | E46: =E45*7% -> 3788.33
D47: Total | E47: =SUM(E45:E46) -> 57907.33

Sheet Depot Repair
A1: Model | B1: Serial | C1: Type | D1: Size | E1: Repair Cost | F1: Parts Summary
A2: AP10-A86-NA-R | B2: AA862Q310AB0090025 | C2: Basic | D2: Large | E2: 135 | F2: PSU Replaced
A3: AP10-B86-NA-R | B3: AB863P521MC25A0058 | C3: Basic | D3: Large | E3: 135 | F3: Mainboard Replaced
A4: AP10-B86-NA-R | B4: AB861PC49TC88B0056 | C4: Basic | D4: Large | E4: 135 | F4: Mainboard Replaced
A5: AP7-B86-02-NA-R | B5: 786T-M46LFA6251160 | C5: Basic | D5: Large | E5: 135 | F5: Maintouch PCA Replaced
A6: AP7-B86-NA-R | B6: 786T-KC2LFA7560083 | C6: Basic | D6: Large | E6: 135 | F6: Maintouch PCA, PSU Replaced
A7: AP7-U86-02-NA-R | B7: 86W26-M1HLDN4010101 | C7: Basic | D7: Large | E7: 135 | F7: Mainboard Replaced
A8: AP7-U86-02-NA-R | B8: 86W26-M5HLDN8090151 | C8: Basic | D8: Large | E8: 135 | F8: PSU Replaced
A9: AP9-A86-NA-R | B9: 9A863M834K21060093 | C9: Basic | D9: Large | E9: 135 | F9: Backlight Tape
A10: AP9-A86-NA-R | B10: 9A862N730VB04A0033 | C10: Basic | D10: Large | E10: 135 | F10: Mainboard Replaced
A11: AP9-B86-NA-R | B11: 9B86BN521TB84A0034 | C11: Basic | D11: Large | E11: 135 | F11: PSU Replaced
A12: AP9-B86-NA-R | B12: 9B86GP834MC58A0030 | C12: Basic | D12: Large | E12: 135 | F12: Mainboard Replaced
A13: AP9-B86-NA-R | B13: 9B86BN522TB93A0030 | C13: Basic | D13: Large | E13: 135 | F13: Mainboard Replaced
... A255: AP9-A75-NA-R | B255: 9A752M727K20870478 | C255: Salvage of Hardware and Scrap | D255: Small | E255: 28 | F255: Harvested: Physical Damage

Sheet Triage Units
A1: Model | B1: Serial | C1: Triage | D1: Derived Type | E1: Size | F1: Cost
A2: AP9-A86-NA-R | B2: 9A861M625K20030093 | C2: Pending Digitizer | D2: BasicLarge-Triage | E2: Large | F2: 101
A3: AP9-A86-NA-R | B3: 9A862N833VB52A0017 | C3: Pending Mainboard | D3: BasicLarge-Triage | E3: Large | F3: 101
A4: AP10-A75-NA-R | B4: AA753Q625AB0050110 | C4: Pending Maintouch PCA | D4: BasicSmall-Triage | E4: Small | F4: 86
A5: AP9-A75-V-NA-R | B5: 9A752NA43VB21A0053 | C5: Pending Mainboard | D5: BasicSmall-Triage | E5: Small | F5: 86
A6: AP10-A86-NA-R | B6: AA862Q310AB0120060 | C6: Pending LCD | D6: HeavyLarge-Triage | E6: Large | F6: 181
A7: AP10-B86-NA-R | B7: AB861P208MC57A0014 | C7: Pending LCM | D7: HeavyLarge-Triage | E7: Large | F7: 181
A8: AP10-B86-NA-R | B8: AB861P312MC78A0050 | C8: Pending LCM | D8: HeavyLarge-Triage | E8: Large | F8: 181
A9: AP9-A86-NA-R | B9: 9A861M730K20550149 | C9: Pending Overlay | D9: HeavyLarge-Triage | E9: Large | F9: 181
A10: AP9-A86-NA-R | B10: 9A861M523K21360389 | C10: Pending LCD | D10: HeavyLarge-Triage | E10: Large | F10: 181
A11: AP9-A86-NA-R | B11: 9A861M728K20530158 | C11: Pending LCD | D11: HeavyLarge-Triage | E11: Large | F11: 181
A12: AP9-A86-NA-R | B12: 9A861M731K20780409 | C12: Pending LCD | D12: HeavyLarge-Triage | E12: Large | F12: 181
A13: AP9-A86-NA-R | B13: 9A861M625K20190279 | C13: Pending LCD | D13: HeavyLarge-Triage | E13: Large | F13: 181
... A131: AP9-B75-NA-R | B131: 9B754M937T101A0098 | C131: Pending LCM | D131: HeavySmall-Triage | E131: Small | F131: 152

Sheet Part Testing & Programming
A1: MSO | B1: Request Date | C1: Outbound Tracking | D1: Part # | E1: Type | F1: Serial | G1: Quantity | H1: Individual Part Fee | I1: Total Programming Fee | J1: Part Pick Fee
A2: M00114902 | B2: 46174 | C2: 872532826995 | D2: AP5-AC-PCA | E2: AC-PCA | F2: 775T-M46LFA5820246 | G2: 1 | H2: 4 | I2: 4 | J2: 8
A3: M00114909 | B3: 46174 | C3: 872533481733 | D3: AP9A-AC-ASSY-75/86 | E3: AC-PCA | F3: 9A756MA44K20710074 | G3: 1 | H3: 0 | I3: 0 | J3: 8
A4: M00114909 | B4: 46174 | C4: 872533481733 | D4: AP9A-CONSOLE | E4: Keypad | F4: 9A756MA44K20710074 | G4: 1 | H4: 0 | I4: 0 | J4: 8
A5: M00114904 | B5: 46174 | C5: 872533139180 | D5: AP9B-CONSOLE | E5: Keypad | F5: 9B652M832T153A0022 | G5: 1 | H5: 0 | I5: 0 | J5: 8
A6: M00114755 | B6: 46174 | C6: 872531590668 | D6: AP9B-CONSOLE | E6: Keypad | F6: 9B75BN625TB68A0014 | G6: 1 | H6: 0 | I6: 0 | J6: 8
A7: M00114779 | B7: 46174 | C7: 872531799811 | D7: AP10A-KEYPAD | E7: Keypad | F7: AA752Q312AB0550078 | G7: 1 | H7: 4 | I7: 4 | J7: 8
A8: M00114902 | B8: 46174 | C8: 872532826995 | D8: AP7B-KEYPAD | E8: Keypad | F8: 775T-M46LFA5820246 | G8: 1 | H8: 4 | I8: 4 | J8: 8
A9: M00114907 | B9: 46174 | C9: 872533349278 | D9: AP7B-KEYPAD | E9: Keypad | F9: 775T-M26BDA2290052 | G9: 1 | H9: 4 | I9: 4 | J9: 8
A10: M00114779 | B10: 46174 | C10: 872531799811 | D10: AP10A-MAINBOARD | E10: Mainboard Configure for Dispatch | F10: AA752Q312AB0550078 | G10: 1 | H10: 52 | I10: 52 | J10: 8
A11: M00114902 | B11: 46174 | C11: 872532826995 | D11: AP7B-MAINBOARD | E11: Mainboard Configure for Dispatch | F11: 775T-M46LFA5820246 | G11: 1 | H11: 52 | I11: 52 | J11: 8
A12: M00114907 | B12: 46174 | C12: 872533349278 | D12: AP7B-MAINBOARD | E12: Mainboard Configure for Dispatch | F12: 775T-M26BDA2290052 | G12: 1 | H12: 52 | I12: 52 | J12: 8
A13: M00114909 | B13: 46174 | C13: 872533481733 | D13: AP9A-MAINBOARD | E13: Mainboard Configure for Dispatch | F13: 9A756MA44K20710074 | G13: 1 | H13: 52 | I13: 52 | J13: 8
... A23: M00114896 | B23: 46174 | C23: 872532181875 | D23: OPS-A1-8R64S | E23: USB | F23: A864124052401300457 | G23: 1 | H23: 4 | I23: 4 | J23: 8
A24: M00114891 | B24: 46174 | C24: 872532047903 | D24: ERCU1-NA-BOXED-1 | F24: AB752P520MC24A0028 | G24: 1 | H24: 0 | I24: 0 | J24: 8
A25: M00114918 | B25: 46175 | C25: 872588003150 | D25: AP9A-CONSOLE | E25: Keypad | F25: 9A752M730K20690004 | G25: 1 | H25: 0 | I25: 0 | J25: 8
A26: M00114661 | B26: 46175 | C26: 872587895800 | D26: AP10B-EXT-INPUT | E26: EXT-INPUT | F26: AB651P312MC68A0004 | G26: 1 | H26: 7 | I26: 7 | J26: 8
A27: M00114661 | B27: 46175 | C27: 872587895800 | D27: AP10B-MAINBOARD | E27: Mainboard Configure for Dispatch | F27: AB651P312MC68A0004 | G27: 1 | H27: 52 | I27: 52 | J27: 8
A28: M00114918 | B28: 46175 | C28: 872588003150 | D28: AP9A-MAINBOARD | E28: Mainboard Configure for Dispatch | F28: 9A752M730K20690004 | G28: 1 | H28: 52 | I28: 52 | J28: 8
A29: M00114926 | B29: 46175 | C29: 872588227038 | D29: AP7B-02-70MAINTOUCHPCA | E29: Maintouch | G29: 1 | H29: 37 | I29: 37 | J29: 8
A30: M00114921 | B30: 46175 | C30: 872588113360 | D30: AP7B-70PSU | E30: PSU | F30: 770T-K62X3A4790005 | G30: 1 | H30: 7 | I30: 7 | J30: 8
A31: M00114918 | B31: 46175 | C31: 872588003150 | D31: AP9A-75PSU | E31: PSU | F31: 9A752M730K20690004 | G31: 1 | H31: 7 | I31: 7 | J31: 8
A32: M00114369 | B32: 46176 | C32: 872641531754 | D32: AP9B-AC-ASSY | E32: AC-PCA | F32: 9A865P415VC48A0030 | G32: 1 | H32: 0 | I32: 0 | J32: 8
A33: M00114369 | B33: 46176 | C33: 872641531754 | D33: AP9A-CONSOLE | E33: Keypad | F33: 9A865P415VC48A0030 | G33: 1 | H33: 0 | I33: 0 | J33: 8
A34: M00114588 | B34: 46176 | C34: 872641767154 | D34: AP9A-CONSOLE | E34: Keypad | F34: 9A652N729VB84A0114 | G34: 1 | H34: 0 | I34: 0 | J34: 8
A35: M00114931 | B35: 46176 | C35: 872642323070 | D35: AP10B-KEYPAD | E35: Keypad | F35: AB752P625MC41A0102 | G35: 1 | H35: 4 | I35: 4 | J35: 8
A36: M00114931 | B36: 46176 | C36: 872642323070 | D36: AP10B-MAINBOARD | E36: Mainboard Configure for Dispatch | F36: AB752P625MC41A0102 | G36: 1 | H36: 52 | I36: 52 | J36: 8
A37: M00114369 | B37: 46176 | C37: 872641531754 | D37: AP9A-MAINBOARD-V | E37: Mainboard Configure for Dispatch | F37: 9A865P415VC48A0030 | G37: 1 | H37: 52 | I37: 52 | J37: 8
A38: M00114588 | B38: 46176 | C38: 872641767154 | D38: AP9A-MAINBOARD-V | E38: Mainboard Configure for Dispatch | F38: 9A652N729VB84A0114 | G38: 1 | H38: 52 | I38: 52 | J38: 8
A39: M00114929 | B39: 46176 | C39: 872642137909 | D39: AP9B-MAINBOARD | E39: Mainboard Configure for Dispatch | F39: 9B75BN522TB74A0065 | G39: 1 | H39: 52 | I39: 52 | J39: 8
A40: M00114942 | B40: 46176 | C40: 872643300432 | D40: AP7B-02-70PSU | E40: PSU | F40: 770T-M26XDA1930184 | G40: 1 | H40: 7 | I40: 7 | J40: 8
A41: M00114588 | B41: 46176 | C41: 872641767154 | D41: AP9B-65PSU | E41: PSU | F41: 9A652N729VB84A0114 | G41: 1 | H41: 7 | I41: 7 | J41: 8
... A74: M00114975 | B74: 46178 | C74: 872776106705 | D74: AP-WIFI-BC | E74: USB | F74: 775T-M46LFA6061017 | G74: 1 | H74: 4 | I74: 4 | J74: 8
A75: M00114947 | B75: 46178 | C75: 872775101578 | D75: ERCU1-NA-BOXED-1 | F75: AB751P314MC81A0081 | G75: 1 | H75: 0 | I75: 0 | J75: 8
A76: M00114953 | B76: 46178 | C76: 872775509054 | D76: ERCU1-NA-BOXED-1 | F76: AB752P625MC49A0154 | G76: 1 | H76: 0 | I76: 0 | J76: 8
A77: M00114976 | B77: 46181 | C77: 872835138703 | D77: AP10B-KEYPAD | E77: Keypad | F77: AB751P312MC72A0043 | G77: 1 | H77: 4 | I77: 4 | J77: 8
A78: M00114976 | B78: 46181 | C78: 872835138703 | D78: AP10B-MAINBOARD | E78: Mainboard Configure for Dispatch | F78: AB751P312MC72A0043 | G78: 1 | H78: 52 | I78: 52 | J78: 8
A79: M00114977 | B79: 46181 | C79: 872835257517 | D79: AP9-WIFIBT-AB | E79: USB | F79: 9B754M939T165A0040 | G79: 1 | H79: 4 | I79: 4 | J79: 8
A80: M00114978 | B80: 46181 | C80: 872835312000 | D80: AP9-WIFIBT-AB | E80: USB | F80: 9B754M939T165A0050 | G80: 1 | H80: 4 | I80: 4 | J80: 8
A81: M00114981 | B81: 46181 | C81: 872835416350 | D81: OPS-C1-CP8R256S | E81: USB | F81: 0WITFQIN25208071 | G81: 1 | H81: 4 | I81: 4 | J81: 8
A82: M00114529 | B82: 46181 | C82: 872834823747 | D82: AP10B-ACCBOX-NA | F82: AB753QA43MC32A0053 | G82: 1 | H82: 0 | I82: 0 | J82: 8
A83: M00114737 | B83: 46181 | C83: 872834958056 | D83: APTASBB400-70 | G83: 1 | H83: 0 | I83: 0 | J83: 8
A84: M00114737 | B84: 46181 | C84: 872863797650 | D84: APTASBB400-70 | G84: 1 | H84: 0 | I84: 0 | J84: 8
A85: M00114737 | B85: 46181 | C85: 872863774811 | D85: APTASBB400-70 | G85: 1 | H85: 0 | I85: 0 | J85: 8
A86: M00114901 | B86: 46182 | C86: 872890726467 | D86: AP9A-AC-ASSY-65 | E86: AC-PCA | F86: 9A652M522K20630166 | G86: 1 | H86: 0 | I86: 0 | J86: 8
A87: M00114901 | B87: 46182 | C87: 872890726467 | D87: AP9A-CONSOLE | E87: Keypad | F87: 9A652M522K20630166 | G87: 1 | H87: 0 | I87: 0 | J87: 8
A88: M00114991 | B88: 46182 | C88: 872891057967 | D88: AP7B-KEYPAD | E88: Keypad | F88: 775T-M26BDA2290052 | G88: 1 | H88: 4 | I88: 4 | J88: 8
A89: M00114948 | B89: 46182 | C89: 872890848453 | D89: AP10A-MAINBOARD | E89: Mainboard Configure for Dispatch | F89: AA751PC49AB0390062 | G89: 1 | H89: 52 | I89: 52 | J89: 8
A90: M00114991 | B90: 46182 | C90: 872891057967 | D90: AP7B-02-MAINBOARD | E90: Mainboard Configure for Dispatch | F90: 775T-M26BDA2290052 | G90: 1 | H90: 52 | I90: 52 | J90: 8
A91: M00114901 | B91: 46182 | C91: 872890726467 | D91: AP9A-MAINBOARD | E91: Mainboard Configure for Dispatch | F91: 9A652M522K20630166 | G91: 1 | H91: 52 | I91: 52 | J91: 8
A92: M00114988 | B92: 46182 | C92: 872890959199 | D92: AP7B-02-70MAINTOUCHPCA | E92: Maintouch | F92: 770T-LA6XBA1211408 | G92: 1 | H92: 37 | I92: 37 | J92: 8
A93: M00114991 | B93: 46182 | C93: 872891057967 | D93: AP7B-02-75PSU | E93: PSU | F93: 775T-M26BDA2290052 | G93: 1 | H93: 7 | I93: 7 | J93: 8
A94: M00114901 | B94: 46182 | C94: 872890726467 | D94: AP9A-65PSU | E94: PSU | F94: 9A652M522K20630166 | G94: 1 | H94: 7 | I94: 7 | J94: 8
A95: M00114948 | B95: 46182 | C95: 872890848453 | D95: AP10A-SPEAKER-L | E95: SPEAKER | F95: AA751PC49AB0390062 | G95: 1 | H95: 4 | I95: 4 | J95: 8
A96: M00114948 | B96: 46182 | C96: 872890848453 | D96: AP10A-SPEAKER-R | E96: SPEAKER | F96: AA751PC49AB0390062 | G96: 1 | H96: 4 | I96: 4 | J96: 8
A97: M00114999 | B97: 46182 | C97: 872891280375 | D97: OPS-A2-8R64S-NA | E97: USB | F97: A864225GT2203100880 | G97: 1 | H97: 4 | I97: 4 | J97: 8
A98: M00114996 | B98: 46182 | C98: 872891165225 | D98: ERCU1-NA-BOXED-1 | F98: AB753QA40MC26A0153 | G98: 1 | H98: 0 | I98: 0 | J98: 8
A99: M00114816 | B99: 46183 | C99: 872994273103 | D99: AP9A-CONSOLE | E99: Keypad | F99: 9A75BN519KB0150141 | G99: 1 | H99: 0 | I99: 0 | J99: 8
A100: M00115007 | B100: 46183 | C100: 872994785409 | D100: APLX-EXT-INPUT | E100: EXT-INPUT | F100: LX651N417KB0950097 | G100: 1 | H100: 7 | I100: 7 | J100: 8
A101: M00115012 | B101: 46183 | C101: 872995088438 | D101: AP7B-KEYPAD | E101: Keypad | F101: 775T-J62U3A5340039 | G101: 1 | H101: 4 | I101: 4 | J101: 8
A102: M00115006 | B102: 46183 | C102: 872994608084 | D102: AP10B-MAINBOARD | E102: Mainboard Configure for Dispatch | F102: AB751P312MC72A0043 | G102: 1 | H102: 52 | I102: 52 | J102: 8
A103: M00115015 | B103: 46183 | C103: 872995291186 | D103: AP7B-MAINBOARD | E103: Mainboard Configure for Dispatch | F103: 775T-J42U3A3170337 | G103: 1 | H103: 52 | I103: 52 | J103: 8
A104: M00115012 | B104: 46183 | C104: 872995088438 | D104: AP7B-MAINBOARD | E104: Mainboard Configure for Dispatch | F104: 775T-J62U3A5340039 | G104: 1 | H104: 52 | I104: 52 | J104: 8
A105: M00114816 | B105: 46183 | C105: 872994273103 | D105: AP9A-MAINBOARD | E105: Mainboard Configure for Dispatch | F105: 9A75BN519KB0150141 | G105: 1 | H105: 52 | I105: 52 | J105: 8
A106: M00115007 | B106: 46183 | C106: 872994785409 | D106: APLX-MAINBOARD | E106: Mainboard Configure for Dispatch | F106: LX651N417KB0950097 | G106: 1 | H106: 52 | I106: 52 | J106: 8
A107: M00114878 | B107: 46183 | C107: 872994390223 | D107: AP7B-02-75MAINTOUCHPCA | E107: Maintouch | F107: 775T-M46LFA6060772 | G107: 1 | H107: 37 | I107: 37 | J107: 8
A108: M00115023 | B108: 46183 | C108: 872995392277 | D108: AP7B-02-75MAINTOUCHPCA | E108: Maintouch | F108: 775T-LB6BCA5630713 | G108: 1 | H108: 37 | I108: 37 | J108: 8
A109: M00115006 | B109: 46183 | C109: 872994608084 | D109: AP10B-OPS-PCA | E109: OPS-PCA | F109: AB751P312MC72A0043 | G109: 1 | H109: 4 | I109: 4 | J109: 8
A110: M00115015 | B110: 46183 | C110: 872995291186 | D110: AP7B-75PSU | E110: PSU | F110: 775T-J42U3A3170337 | G110: 1 | H110: 7 | I110: 7 | J110: 8
... A115: M00115011 | B115: 46183 | C115: 872995002903 | D115: OPS-A2-8R64S-NA | E115: USB | F115: A864225FT2001601416 | G115: 1 | H115: 4 | I115: 4 | J115: 8
A116: M00115002 | B116: 46183 | C116: 872994492858 | D116: AP9-POWER-CABLE-US | F116: 9A75GP937KB0420336 | G116: 1 | H116: 0 | I116: 0 | J116: 8
A117: M00115010 | B117: 46183 | C117: 872994901044 | D117: ERCU1-NA-BOXED-1 | F117: AB554R209MC15A0188 | G117: 1 | H117: 0 | I117: 0 | J117: 8
A118: M00115043 | B118: 46184 | C118: 872996215103 | D118: AP6-65-AC-PCA | E118: AC-PCA | F118: 770T-M16XCA0020195 | G118: 1 | H118: 4 | I118: 4 | J118: 8
A119: M00114845 | B119: 46184 | C119: 872995870997 | D119: AP9B-EXT-INPUT | E119: EXT-INPUT | F119: 9B86GP415TC97A0023 | G119: 1 | H119: 7 | I119: 7 | J119: 8
A120: M00115030 | B120: 46184 | C120: 872996071130 | D120: AP10A-KEYPAD | E120: Keypad | F120: AA653Q728AB0140038 | G120: 1 | H120: 4 | I120: 4 | J120: 8
A121: M00115043 | B121: 46184 | C121: 872996215103 | D121: AP7B-KEYPAD | E121: Keypad | F121: 770T-M16XCA0020195 | G121: 1 | H121: 4 | I121: 4 | J121: 8
A122: M00115030 | B122: 46184 | C122: 872996071130 | D122: AP10A-MAINBOARD | E122: Mainboard Configure for Dispatch | F122: AA653Q728AB0140038 | G122: 1 | H122: 52 | I122: 52 | J122: 8
A123: M00115043 | B123: 46184 | C123: 872996215103 | D123: AP7B-02-MAINBOARD | E123: Mainboard Configure for Dispatch | F123: 770T-M16XCA0020195 | G123: 1 | H123: 52 | I123: 52 | J123: 8
A124: M00114845 | B124: 46184 | C124: 872995870997 | D124: AP9B-MAINBOARD-2 | E124: Mainboard Configure for Dispatch | F124: 9B86GP415TC97A0023 | G124: 1 | H124: 52 | I124: 52 | J124: 8
A125: M00114840 | B125: 46184 | C125: 872995741299 | D125: AP7B-02-75MAINTOUCHPCA | E125: Maintouch | F125: 775T-M36BDA3790316 | G125: 1 | H125: 37 | I125: 37 | J125: 8
A126: M00114840 | B126: 46184 | C126: 872995741299 | D126: AP7B-75MAINTOUCHPCA | E126: Maintouch | F126: 775T-M36BDA3790316 | G126: 1 | H126: 37 | I126: 37 | J126: 8
A127: M00115043 | B127: 46184 | C127: 872996215103 | D127: AP7B-02-70PSU | E127: PSU | F127: 770T-M16XCA0020195 | G127: 1 | H127: 7 | I127: 7 | J127: 8
A128: M00115028 | B128: 46184 | C128: 872995978729 | D128: OPS3-5P8R256S | E128: USB | F128: G256S221100044403 | G128: 1 | H128: 4 | I128: 4 | J128: 8
A129: M00115054 | B129: 46185 | C129: 873089054425 | D129: AP9A-CONSOLE | E129: Keypad | F129: 9A752M623K21350541 | G129: 1 | H129: 0 | I129: 0 | J129: 8
... A140: M00115047 | B140: 46185 | C140: 873088674379 | D140: OPS-A2-8R64S-NA | E140: USB | F140: A864225FT2001601491 | G140: 1 | H140: 4 | I140: 4 | J140: 8
A141: M00114826 | B141: 46185 | C141: 873087899143 | D141: 481A71001 | F141: A864225IT2901202297 | G141: 1 | H141: 0 | I141: 0 | J141: 8
A142: M00114826 | B142: 46185 | C142: 873087899143 | D142: 481A71001 | F142: A864225IT2901202297 | G142: 1 | H142: 0 | I142: 0 | J142: 8
A143: M00114892 | B143: 46185 | C143: 873088246209 | D143: WH3310-LK | G143: 1 | H143: 0 | I143: 0 | J143: 8
A144: M00115091 | B144: 46188 | C144: 873160582135 | D144: AP7B-EXT-INPUT | E144: EXT-INPUT | F144: 770T-LB6XCA7380410 | G144: 1 | H144: 7 | I144: 7 | J144: 8
A145: M00114954 | B145: 46188 | C145: 873158209156 | D145: APLX-EXT-INPUT | E145: EXT-INPUT | F145: LX754NC49AB0200061 | G145: 1 | H145: 7 | I145: 7 | J145: 8
A146: M00115090 | B146: 46188 | C146: 873160382482 | D146: APLX-KEYPAD | E146: Keypad | F146: LX753N727AB0100082 | G146: 1 | H146: 4 | I146: 4 | J146: 8
A147: M00115083 | B147: 46188 | C147: 873159101799 | D147: APLX-KEYPAD | E147: Keypad | F147: LX654NA40AB0130002 | G147: 1 | H147: 4 | I147: 4 | J147: 8
A148: M00115094 | B148: 46188 | C148: 873160733430 | D148: AP7B-MAINBOARD | E148: Mainboard Configure for Dispatch | F148: 775T-L76U4A4230292 | G148: 1 | H148: 52 | I148: 52 | J148: 8
A149: M00115091 | B149: 46188 | C149: 873160582135 | D149: AP7B-MAINBOARD | E149: Mainboard Configure for Dispatch | F149: 770T-LB6XCA7380410 | G149: 1 | H149: 52 | I149: 52 | J149: 8
A150: M00115082 | B150: 46188 | C150: 873158948943 | D150: AP9B-MAINBOARD | E150: Mainboard Configure for Dispatch | F150: 9B652M624T112A0050 | G150: 1 | H150: 52 | I150: 52 | J150: 8
A151: M00115103 | B151: 46188 | C151: 873160916043 | D151: AP9B-MAINBOARD | E151: Mainboard Configure for Dispatch | F151: 9B75GP521TB76A0068 | G151: 1 | H151: 52 | I151: 52 | J151: 8
A152: M00115090 | B152: 46188 | C152: 873160382482 | D152: APLX-MAINBOARD | E152: Mainboard Configure for Dispatch | F152: LX753N727AB0100082 | G152: 1 | H152: 52 | I152: 52 | J152: 8
A153: M00114954 | B153: 46188 | C153: 873158209156 | D153: APLX-MAINBOARD | E153: Mainboard Configure for Dispatch | F153: LX754NC49AB0200061 | G153: 1 | H153: 52 | I153: 52 | J153: 8
A154: M00115083 | B154: 46188 | C154: 873159101799 | D154: APLX-MAINBOARD | E154: Mainboard Configure for Dispatch | F154: LX654NA40AB0130002 | G154: 1 | H154: 52 | I154: 52 | J154: 8
A155: M00115084 | B155: 46188 | C155: 873159310192 | D155: AP10B-OPS-PCA | E155: OPS-PCA | F155: AB751P310MC71A0040 | G155: 1 | H155: 4 | I155: 4 | J155: 8
...
